steinlib/__init__.py
steinlib/exceptions.py
steinlib/instance.py
steinlib/parser.py
steinlib/section.py
steinlib/state.py
steinlib-0.1.dist-info/DESCRIPTION.rst
steinlib-0.1.dist-info/METADATA
steinlib-0.1.dist-info/RECORD
steinlib-0.1.dist-info/WHEEL
steinlib-0.1.dist-info/metadata.json
steinlib-0.1.dist-info/top_level.txt
