Metadata-Version: 2.0
Name: steinlib
Version: 0.1
Summary: Python bindings for Steinlib format.
Home-page: http://github.com/leandron/steinlib
Author: Leandro Nunes
Author-email: leandron85@gmail.com
License: MIT
Platform: UNKNOWN
